r2client/R2Client.py
r2client/__init__.py
r2client/mime_types.py
r2client-0.3.1.dist-info/licenses/LICENSE
r2client-0.3.1.dist-info/METADATA
r2client-0.3.1.dist-info/WHEEL
r2client-0.3.1.dist-info/top_level.txt
r2client-0.3.1.dist-info/RECORD
