Metadata-Version: 2.4
Name: r2client
Version: 0.3.1
Summary: A lightweight framework to manage your R2 bucket.
Home-page: https://github.com/fayharinn/R2-Client
Author: Fayhe
License: MIT
Requires-Python: >=3.6
License-File: LICENSE
Requires-Dist: requests
Dynamic: author
Dynamic: description
Dynamic: description-content-type
Dynamic: home-page
Dynamic: license
Dynamic: license-file
Dynamic: requires-dist
Dynamic: requires-python
Dynamic: summary
